Metadata-Version: 2.1
Name: KGIapi
Version: 0.2
Summary: My test project
Author: Louis Hsu
Author-email: Louis.Hsu@kgi.com
License-File: LICENSE
